MANIFEST.in
README.rst
buildout.cfg
setup.cfg
setup.py
docs/CHANGES.rst
docs/CONTRIBUTORS.rst
docs/LICENSE.txt
src/sphinxcontrib/__init__.py
src/sphinxcontrib/gen_node.py
src/sphinxcontrib_gen_node.egg-info/PKG-INFO
src/sphinxcontrib_gen_node.egg-info/SOURCES.txt
src/sphinxcontrib_gen_node.egg-info/dependency_links.txt
src/sphinxcontrib_gen_node.egg-info/namespace_packages.txt
src/sphinxcontrib_gen_node.egg-info/not-zip-safe
src/sphinxcontrib_gen_node.egg-info/requires.txt
src/sphinxcontrib_gen_node.egg-info/top_level.txt