Metadata-Version: 1.1
Name: sphinxcontrib-gen-node
Version: 0.1-20131031
Summary: Sphinx generic nodes "todo like" extension
Home-page: https://github.com/jpcw/sphinxcontrib-gen_node
Author: Jean-Philippe Camguilhem
Author-email: jean-philippe.camguilhem__at__makina-corpus.com
License: BSD
Download-URL: http://pypi.python.org/pypi/sphinxcontrib-gen_node
Platform: any
Classifier: Development Status :: 4 - Beta
Classifier: Environment :: Console
Classifier: Environment :: Web Environment
Classifier: Intended Audience :: Developers
Classifier: License :: OSI Approved :: BSD License
Classifier: Operating System :: OS Independent
Classifier: Programming Language :: Python
Classifier: Topic :: Documentation
Classifier: Topic :: Utilities
